databaseauto/__init__.py
databaseauto/mongo_crud.py
databaseauto-5.0.0.dist-info/METADATA
databaseauto-5.0.0.dist-info/WHEEL
databaseauto-5.0.0.dist-info/top_level.txt
databaseauto-5.0.0.dist-info/RECORD
